docs/source/conf.py
overleaf_fs/__init__.py
overleaf_fs/app.py
overleaf_fs/cli.py
overleaf_fs/core/__init__.py
overleaf_fs/core/config.py
overleaf_fs/core/directory_structure_store.py
overleaf_fs/core/models.py
overleaf_fs/core/overleaf_scraper.py
overleaf_fs/core/profiles.py
overleaf_fs/core/project_index.py
overleaf_fs/gui/__init__.py
overleaf_fs/gui/main_window.py
overleaf_fs/gui/overleaf_login.py
overleaf_fs/gui/profile_manager.py
overleaf_fs/gui/profile_root_ui.py
overleaf_fs/gui/project_table.py
overleaf_fs/gui/project_table_model.py
overleaf_fs/gui/project_tree.py
overleaf_fs-0.1.4.dist-info/licenses/LICENSE
tests/__init__.py
tests/test_core.py
tests/test_smoke_gui.py
tests/manual/test_external_change.py
overleaf_fs-0.1.4.dist-info/METADATA
overleaf_fs-0.1.4.dist-info/WHEEL
overleaf_fs-0.1.4.dist-info/entry_points.txt
overleaf_fs-0.1.4.dist-info/top_level.txt
overleaf_fs-0.1.4.dist-info/RECORD
