Metadata-Version: 2.4
Name: overleaf_fs
Version: 0.1.4
Summary: GUI-based project organization for Overleaf
Author-email: Greg Buzzard <buzzard@purdue.edu>
License: BSD 3-Clause License
Project-URL: homepage, https://overleaf-fs.readthedocs.io
Project-URL: source, https://github.com/gbuzzard/overleaf_fs
Keywords: overleaf,file system
Classifier: Programming Language :: Python :: 3
Classifier: Topic :: Scientific/Engineering :: Information Analysis
Classifier: License :: OSI Approved :: BSD License
Classifier: Operating System :: OS Independent
Requires-Python: >=3.9
License-File: LICENSE
Requires-Dist: PySide6>=6.7
Requires-Dist: requests
Requires-Dist: bs4
Provides-Extra: test
Requires-Dist: pytest; extra == "test"
Provides-Extra: docs
Requires-Dist: sphinx; extra == "docs"
Requires-Dist: sphinxcontrib-bibtex; extra == "docs"
Requires-Dist: sphinx-book-theme>=1.0.1; extra == "docs"
Requires-Dist: sphinx-design; extra == "docs"
Requires-Dist: sphinx-copybutton; extra == "docs"
Provides-Extra: dev
Requires-Dist: pyinstaller; extra == "dev"
Requires-Dist: build; extra == "dev"
Dynamic: license-file
